{
    "pools": [
      {
        "rolls": 1,
        "entries": [
          {
            "type": "minecraft:item",
            "name": "minecraft:warped_fungus_on_a_stick",
            "functions": [
              {
                "function": "minecraft:set_nbt",
                "tag": "{CustomModelData:6,LinkSight:1b,ShopTool:1b}"
              },
              {
                "function": "minecraft:set_name",
                "entity": "this",
                "name": {
                  "text": "Storage Link Sight Tool",
                  "color": "green",
                  "italic": false
                }
              },
              {
                "function": "minecraft:set_lore",
                "entity": "this",
                "lore": [
                  {
                    "text": "Lets you see any shop container's links",
                    "color": "gray",
                    "italic": false
                  },
                  {
                    "text": "with storages",
                    "color": "gray",
                    "italic": false
                  },
                  {
                    "text": " ",
                    "color": "gray",
                    "italic": false
                  },
                  [
                    {
                      "text": "Green",
                      "color": "green",
                      "italic": false
                    },
                    {
                      "text": " laser means income. (What the vendor will obtain)",
                      "color": "gray",
                      "italic": false
                    }
                  ],
                  [
                    {
                      "text": "Red",
                      "color": "red",
                      "italic": false
                    },
                    {
                      "text": " laser means stock. (What the vendor will sell)",
                      "color": "gray",
                      "italic": false
                    }
                  ]
                ]
              }
            ]
          }
        ]
      }
    ]
  }
